{
    "A01版：头版.pdf": {
        "id": "iluwm1wlnbpe",
        "size": "2.2 M"
    },
    "A02版：城事.pdf": {
        "id": "iSYeU1wlnbqf",
        "size": "1.0 M"
    },
    "A03版：众志成城 抗击疫情.pdf": {
        "id": "ii7CE1wlnbnc",
        "size": "1.8 M"
    },
    "A04版：城事.pdf": {
        "id": "iepFL1wlnbih",
        "size": "3.2 M"
    },
    "A05版：城事.pdf": {
        "id": "iGs1v1wlnbgf",
        "size": "860.7 K"
    },
    "A06版：社会.pdf": {
        "id": "iXsew1wlnbla",
        "size": "1.2 M"
    },
    "A07版：热点.pdf": {
        "id": "i7Cts1wlnbsh",
        "size": "1.2 M"
    },
    "A08版：公益.pdf": {
        "id": "ibaHC1wlnbkj",
        "size": "3.5 M"
    }
}