{
    "01版：要闻.pdf": {
        "id": "i29XS1we5wkf",
        "size": "3.1 M"
    },
    "02版：要闻.pdf": {
        "id": "iZNYU1we5wej",
        "size": "2.7 M"
    },
    "03版：要闻.pdf": {
        "id": "i22Kg1we5whc",
        "size": "3.7 M"
    },
    "04版：要闻.pdf": {
        "id": "iyUbl1we5wfa",
        "size": "2.7 M"
    },
    "05版：军营观察.pdf": {
        "id": "i1Q9C1we5wmh",
        "size": "3.7 M"
    },
    "06版：八一评论.pdf": {
        "id": "idZ5i1we5wbg",
        "size": "565.4 K"
    },
    "07版：思想战线.pdf": {
        "id": "iDGFE1we5wlg",
        "size": "567.2 K"
    },
    "08版：基层传真.pdf": {
        "id": "igTGm1we5wni",
        "size": "2.6 M"
    },
    "09版：兵器大观.pdf": {
        "id": "iB3me1we5wje",
        "size": "3.2 M"
    },
    "10版：国防军工.pdf": {
        "id": "iRRAU1we5wgb",
        "size": "1.2 M"
    },
    "11版：科技前沿.pdf": {
        "id": "iHAIb1we5wdi",
        "size": "1.2 M"
    },
    "12版：长征副刊.pdf": {
        "id": "iKFFb1we5wch",
        "size": "1.9 M"
    }
}