{
    "01版：要闻.pdf": {
        "id": "iN4FT1wejhnc",
        "size": "1.1 M"
    },
    "02版：要闻.pdf": {
        "id": "iDbwp1wejhsh",
        "size": "1.7 M"
    },
    "03版：要闻.pdf": {
        "id": "irQL11wejhmb",
        "size": "955.4 K"
    },
    "04版：要闻.pdf": {
        "id": "ixbuR1wejhpe",
        "size": "1,011.7 K"
    },
    "05版：军人家庭.pdf": {
        "id": "iNkET1wejhuj",
        "size": "889.4 K"
    },
    "06版：文化生活.pdf": {
        "id": "ieuL01weji0f",
        "size": "918.4 K"
    },
    "07版：军人健康.pdf": {
        "id": "iAQn91wejhyd",
        "size": "868.1 K"
    },
    "08版：长征副刊.pdf": {
        "id": "iQgS21wejhwb",
        "size": "1.0 M"
    }
}