{
    "A02版：要聞.pdf": {
        "id": "ioDJN1v3c42j",
        "size": "2.3 M"
    },
    "A03版：要聞.pdf": {
        "id": "iNoSa1v3c49g",
        "size": "1.4 M"
    },
    "A04版：要聞.pdf": {
        "id": "immWq1v3c4he",
        "size": "1.1 M"
    },
    "A05版：中國新聞.pdf": {
        "id": "iXyoc1v3c4pc",
        "size": "2.0 M"
    },
    "A06版：中國新聞.pdf": {
        "id": "i7HK81v3c4uh",
        "size": "1.0 M"
    },
    "A07版：中國新聞.pdf": {
        "id": "iTjVu1v3c51e",
        "size": "778.6 K"
    },
    "A08版：港聞.pdf": {
        "id": "iRoz11v3c57a",
        "size": "1.5 M"
    },
    "A09版：港聞.pdf": {
        "id": "iBgXE1v3c5dg",
        "size": "926.4 K"
    },
    "A10版：港聞.pdf": {
        "id": "iiYPz1v3c5ha",
        "size": "1.4 M"
    },
    "A11版：港聞.pdf": {
        "id": "i6ZOb1v3c5kd",
        "size": "1.4 M"
    },
    "A12版：港聞.pdf": {
        "id": "ihWi21v3c5ra",
        "size": "2.1 M"
    },
    "A13版：大珠三角.pdf": {
        "id": "iKnMH1v3c5yh",
        "size": "1.9 M"
    },
    "A14版：海峽兩岸.pdf": {
        "id": "iyJll1v3c62b",
        "size": "1.5 M"
    },
    "A15版：海南專題‧台灣新聞.pdf": {
        "id": "ig2uC1v3c69i",
        "size": "2.0 M"
    },
    "A16版：大公評論.pdf": {
        "id": "iNse51v3c6ba",
        "size": "793.9 K"
    },
    "A17版：大公評論.pdf": {
        "id": "ipxK31v3c6gf",
        "size": "864.5 K"
    },
    "A18版：賽馬結果.pdf": {
        "id": "i2esf1v3c6ji",
        "size": "996.4 K"
    },
    "A19版：國際新聞.pdf": {
        "id": "iUChW1v3c6mb",
        "size": "1.7 M"
    },
    "A20版：國際新聞.pdf": {
        "id": "i2umm1v3c6qf",
        "size": "1.2 M"
    },
    "B01版：大公經濟.pdf": {
        "id": "icHlm1v3c6va",
        "size": "1.3 M"
    },
    "B02版：經濟.pdf": {
        "id": "iXRzb1v3c6xc",
        "size": "1.2 M"
    },
    "B03版：地產.pdf": {
        "id": "izDq01v3c75a",
        "size": "4.3 M"
    },
    "B04版：投資全方位.pdf": {
        "id": "ijFPs1v3c78d",
        "size": "988.4 K"
    },
    "B05版：股市行情.pdf": {
        "id": "ipnLg1v3c7bg",
        "size": "1.2 M"
    },
    "B06版：股市行情.pdf": {
        "id": "iK0cL1v3c7di",
        "size": "1.4 M"
    },
    "B07版：股市行情.pdf": {
        "id": "iWAxY1v3c7id",
        "size": "1.8 M"
    },
    "B08版：物流與航運.pdf": {
        "id": "iJA8l1v3c7mh",
        "size": "1.3 M"
    },
    "B09版：中國證券.pdf": {
        "id": "iFy4Z1v3c7pa",
        "size": "1.1 M"
    },
    "B10版：中國經濟.pdf": {
        "id": "iJ2jf1v3c7uf",
        "size": "1.8 M"
    },
    "C01版：社團新訊.pdf": {
        "id": "iKame1v3c7za",
        "size": "3.2 M"
    },
    "C02版：文化.pdf": {
        "id": "iIOej1v3c84f",
        "size": "2.9 M"
    },
    "C03版：娛樂.pdf": {
        "id": "igy0c1v3c87i",
        "size": "1.2 M"
    },
    "C04版：大公園.pdf": {
        "id": "iRp6U1v3c89a",
        "size": "925.9 K"
    },
    "C05版：新園地‧校園.pdf": {
        "id": "iK3F41v3c8ef",
        "size": "1.4 M"
    },
    "C06版：娛樂.pdf": {
        "id": "iQxRS1v3c8ij",
        "size": "1.9 M"
    },
    "C07版：娛樂.pdf": {
        "id": "ijemC1v3c8lc",
        "size": "1.2 M"
    },
    "C08版：娛樂.pdf": {
        "id": "iO7OZ1v3c8of",
        "size": "1.5 M"
    }
}