{
    "01版：兵团时政.pdf": {
        "id": "ikggR1uzxt9i",
        "size": "4.1 M"
    },
    "02版：要闻.pdf": {
        "id": "itzBm1uzxtba",
        "size": "517.3 K"
    },
    "03版：要闻.pdf": {
        "id": "iq9bE1uzxtji",
        "size": "5.7 M"
    },
    "04版：今日关注.pdf": {
        "id": "igoJO1uzxtsh",
        "size": "5.4 M"
    },
    "05版：援疆特刊.pdf": {
        "id": "ijtF71uzxu3i",
        "size": "13.0 M"
    },
    "06版_07版：援疆特刊.pdf": {
        "id": "iJaPV1uzxukf",
        "size": "13.0 M"
    },
    "08版：援疆特刊.pdf": {
        "id": "izELD1uzxuvg",
        "size": "8.0 M"
    }
}