{
    "01版：要闻.pdf": {
        "id": "iDWSk1wwywvi",
        "size": "1.3 M"
    },
    "02版：要闻.pdf": {
        "id": "i7cwC1wwywzc",
        "size": "575.3 K"
    },
    "03版：要闻.pdf": {
        "id": "ihSha1wwywre",
        "size": "1.0 M"
    },
    "04版：要闻.pdf": {
        "id": "ibxAN1wwywsf",
        "size": "1.2 M"
    },
    "05版：环球扫描.pdf": {
        "id": "iGjdJ1wwywob",
        "size": "1.2 M"
    },
    "06版：要闻.pdf": {
        "id": "iGdsV1wwywpc",
        "size": "747.6 K"
    },
    "07版：旅游天地.pdf": {
        "id": "iXXBI1wwywtg",
        "size": "791.0 K"
    },
    "08版：走进博物馆.pdf": {
        "id": "iRHE91wwywwj",
        "size": "938.7 K"
    }
}