{
    "01版：要闻.pdf": {
        "id": "ixplS1whhhoj",
        "size": "1.0 M"
    },
    "02版：要闻.pdf": {
        "id": "iP6561whhi8j",
        "size": "1.0 M"
    },
    "03版：要闻.pdf": {
        "id": "ifceC1whhhpa",
        "size": "1.1 M"
    },
    "04版：要闻.pdf": {
        "id": "iR8mb1whhide",
        "size": "478.8 K"
    },
    "05版：要闻.pdf": {
        "id": "iUhHq1whhi4f",
        "size": "703.6 K"
    },
    "06版：世界经济.pdf": {
        "id": "isZkX1whhhkf",
        "size": "1.1 M"
    },
    "07版：财金.pdf": {
        "id": "iPeOq1whhhje",
        "size": "1,009.7 K"
    },
    "08版：时评.pdf": {
        "id": "ivRc51whhi0b",
        "size": "926.9 K"
    },
    "09版：特别报道.pdf": {
        "id": "ivcFx1whhhuf",
        "size": "4.3 M"
    },
    "10版：特别报道.pdf": {
        "id": "iZ1XQ1whhief",
        "size": "2.1 M"
    },
    "11版：特别报道.pdf": {
        "id": "iFlhJ1whhhhc",
        "size": "2.4 M"
    },
    "12版：特别报道.pdf": {
        "id": "iXqwu1whhhch",
        "size": "3.0 M"
    }
}