{
    "A01版：头版.pdf": {
        "id": "iYLOx1wzotqd",
        "size": "6.9 M"
    },
    "A02版：今日关注.pdf": {
        "id": "iZNo01wzos9a",
        "size": "5.8 M"
    },
    "A03版：政经要闻.pdf": {
        "id": "in1VL1wzosgh",
        "size": "3.5 M"
    },
    "A04版：综合新闻.pdf": {
        "id": "iMITv1wzotda",
        "size": "3.6 M"
    },
    "A05版：关注.pdf": {
        "id": "ilqO71wzorpa",
        "size": "8.3 M"
    },
    "A06版：综合新闻.pdf": {
        "id": "ih1cB1wzotwj",
        "size": "2.0 M"
    },
    "A07版：都市新闻.pdf": {
        "id": "iT4pd1wzoryj",
        "size": "4.4 M"
    },
    "A08版：财经.pdf": {
        "id": "iPlZm1wzosmd",
        "size": "2.1 M"
    },
    "A09版：证券资讯.pdf": {
        "id": "i4EY11wzot6d",
        "size": "3.4 M"
    },
    "A10版：都市新闻.pdf": {
        "id": "i78BM1wzor5a",
        "size": "1.1 M"
    },
    "A11版：文化广场.pdf": {
        "id": "ieOGB1wzosyf",
        "size": "6.6 M"
    },
    "A12版：科创线.pdf": {
        "id": "iLlL91wzorbg",
        "size": "2.8 M"
    }
}