{
    "A01版：要闻.pdf": {
        "id": "i5jzP1w2hnqh",
        "size": "1.8 M"
    },
    "A02版_A15版：要闻.pdf": {
        "id": "i6Hha1w2hnta",
        "size": "2.9 M"
    },
    "A03版：要闻.pdf": {
        "id": "iQ3Qw1w2hnvc",
        "size": "920.6 K"
    },
    "A04版：要闻.pdf": {
        "id": "ipxWc1w2hnxe",
        "size": "1.3 M"
    },
    "A05版：要闻.pdf": {
        "id": "i7ULS1w2hnyf",
        "size": "1.4 M"
    },
    "A06版：港闻.pdf": {
        "id": "iCN9t1w2ho0h",
        "size": "1.0 M"
    },
    "A07版：文化.pdf": {
        "id": "imw7V1w2ho3a",
        "size": "1.9 M"
    },
    "A08版：港闻.pdf": {
        "id": "i2QLo1w2hoah",
        "size": "1.1 M"
    },
    "A09版：内地.pdf": {
        "id": "iMkNJ1w2hobi",
        "size": "1.1 M"
    },
    "A10版：两岸.pdf": {
        "id": "i6Hib1w2hoda",
        "size": "1.7 M"
    },
    "A11版：国际.pdf": {
        "id": "iTt0r1w2hofc",
        "size": "1.3 M"
    },
    "A12版：经济.pdf": {
        "id": "izArx1w2hohe",
        "size": "872.4 K"
    },
    "A13版：专题.pdf": {
        "id": "iOqZH1w2hojg",
        "size": "1.6 M"
    },
    "A14版：体育.pdf": {
        "id": "i0xKR1w2holi",
        "size": "1.6 M"
    },
    "A16版：国际.pdf": {
        "id": "iBQ951w2hona",
        "size": "3.4 M"
    },
    "B01版：广告.pdf": {
        "id": "iRyp41w2hoob",
        "size": "937.9 K"
    },
    "B02版：经济.pdf": {
        "id": "i8SOh1w2hoqd",
        "size": "1.1 M"
    },
    "B03版：经济.pdf": {
        "id": "ik9x51w2hosf",
        "size": "1.3 M"
    },
    "B04版：专题.pdf": {
        "id": "ibKbA1w2hotg",
        "size": "1.3 M"
    },
    "B05版：特刊.pdf": {
        "id": "iIRbQ1w2howj",
        "size": "1.5 M"
    },
    "B06版：青年.pdf": {
        "id": "i4m701w2hoxa",
        "size": "654.4 K"
    },
    "B07版：副刊.pdf": {
        "id": "iT4ef1w2hp1e",
        "size": "3.6 M"
    },
    "B08版：副刊.pdf": {
        "id": "i6WSR1w2hp3g",
        "size": "867.6 K"
    }
}