{
    "01版：一版要闻.pdf": {
        "id": "ihFAM23mrx4h",
        "size": "1.7 M"
    },
    "02版：出版报道.pdf": {
        "id": "iyHk523mrxle",
        "size": "913.7 K"
    },
    "03版：出版报道.pdf": {
        "id": "idHqC23mry4d",
        "size": "1.0 M"
    },
    "04版：精品导读.pdf": {
        "id": "ie5LD23mrync",
        "size": "1.4 M"
    },
    "05版：分销新视野.pdf": {
        "id": "iXntT23mrz5a",
        "size": "1.5 M"
    },
    "06版：分销新视野.pdf": {
        "id": "iIYES23mrzmh",
        "size": "852.8 K"
    },
    "07版：传媒新媒.pdf": {
        "id": "iQ97p23ms01c",
        "size": "948.8 K"
    },
    "08版：资讯.pdf": {
        "id": "ibPtf23ms0ef",
        "size": "823.3 K"
    },
    "09版：中国阅读·选品指南.pdf": {
        "id": "iPSIZ23ms18f",
        "size": "2.0 M"
    },
    "10版：中国阅读·选品指南·月览.pdf": {
        "id": "iBS0C23ms1ob",
        "size": "1.5 M"
    },
    "11版：中国阅读·选品指南·月览.pdf": {
        "id": "igfru23ms24h",
        "size": "1.6 M"
    },
    "12版：精品导读.pdf": {
        "id": "iYiSj23ms2le",
        "size": "1.3 M"
    }
}