{
    "01版：头版.pdf": {
        "id": "icBKl2a6hd1a",
        "size": "884.1 K"
    },
    "02版：长春新闻.pdf": {
        "id": "i13xf2a6hd6f",
        "size": "1.4 M"
    },
    "03版：长春关注.pdf": {
        "id": "iNtZe2a6hdcb",
        "size": "1.9 M"
    },
    "04版：长春城事.pdf": {
        "id": "ig1nT2a6hdnc",
        "size": "3.7 M"
    },
    "05版_08版：教育.pdf": {
        "id": "iELRC2a6hdva",
        "size": "2.3 M"
    },
    "06版：长春扫描.pdf": {
        "id": "i65r22a6he3i",
        "size": "1.7 M"
    },
    "07版：博闻天下.pdf": {
        "id": "ihhXQ2a6hech",
        "size": "820.8 K"
    },
    "09版：成长课堂.pdf": {
        "id": "irCRI2a6heje",
        "size": "1.5 M"
    },
    "10版：文体之苑.pdf": {
        "id": "ifxhk2a6hevg",
        "size": "2.8 M"
    }
}