{
    "A01版：头条要闻.pdf": {
        "id": "iE6g01wsaasf",
        "size": "1.2 M"
    },
    "A02版：时评.pdf": {
        "id": "icKlR1wsaaxa",
        "size": "1.1 M"
    },
    "A03版：本市.pdf": {
        "id": "iMQak1wsaaob",
        "size": "4.3 M"
    },
    "A04版：本市.pdf": {
        "id": "iVpRK1wsaawj",
        "size": "3.7 M"
    },
    "A05版：本市.pdf": {
        "id": "iNtnj1wsaaqd",
        "size": "885.3 K"
    },
    "A06版：本市.pdf": {
        "id": "ibACg1wsaapc",
        "size": "3.6 M"
    },
    "A07版：本市.pdf": {
        "id": "iadIj1wsaatg",
        "size": "2.3 M"
    },
    "A08版：视觉.pdf": {
        "id": "iDmP51wsaajg",
        "size": "7.0 M"
    },
    "A09版：关注.pdf": {
        "id": "iEgMM1wsaana",
        "size": "1.4 M"
    },
    "A10版：关注.pdf": {
        "id": "inUgq1wsaayb",
        "size": "2.3 M"
    },
    "A11版：国内.pdf": {
        "id": "iBxp31wsaakh",
        "size": "2.3 M"
    },
    "A12版：国内.pdf": {
        "id": "i96Rc1wsaaif",
        "size": "2.0 M"
    },
    "A13版：国际.pdf": {
        "id": "iFhRj1wsaauh",
        "size": "1.8 M"
    },
    "A14版：国际.pdf": {
        "id": "iWtTY1wsaali",
        "size": "1,006.7 K"
    },
    "A15版：体育.pdf": {
        "id": "iCGo21wsaamj",
        "size": "2.1 M"
    },
    "A16版：副刊.pdf": {
        "id": "iKVct1wsaare",
        "size": "2.0 M"
    }
}