{
    "A01版：头版.pdf": {
        "id": "iHyCe1wjxrtc",
        "size": "2.0 M"
    },
    "A02版：特稿.pdf": {
        "id": "iNrm91wjxr8b",
        "size": "712.9 K"
    },
    "A03版：特别报道.pdf": {
        "id": "ifoxz1wjxr4h",
        "size": "597.4 K"
    },
    "A04版：特别报道.pdf": {
        "id": "ieOXk1wjxqyb",
        "size": "464.6 K"
    },
    "A05版：特别报道.pdf": {
        "id": "ifCaR1wjxr0d",
        "size": "639.5 K"
    },
    "A06版：社会.pdf": {
        "id": "iFi741wjxrha",
        "size": "389.5 K"
    },
    "A07版：服务.pdf": {
        "id": "iJGBg1wjxr1e",
        "size": "1.4 M"
    },
    "A08版：广告.pdf": {
        "id": "iw5dQ1wjxrmf",
        "size": "4.3 M"
    },
    "A09版：悦读.pdf": {
        "id": "ig8TC1wjxrqj",
        "size": "5.5 M"
    },
    "A10版：互动.pdf": {
        "id": "irBg81wjxqvi",
        "size": "784.9 K"
    },
    "A11版：热点.pdf": {
        "id": "ia9Ou1wjxrxg",
        "size": "425.2 K"
    },
    "A12版：国内.pdf": {
        "id": "iyCaj1wjxrib",
        "size": "729.1 K"
    },
    "A13版：国际.pdf": {
        "id": "iQNxQ1wjxqtg",
        "size": "564.5 K"
    },
    "A14版：时评.pdf": {
        "id": "ilODt1wjxr2f",
        "size": "462.4 K"
    },
    "A15版：体育.pdf": {
        "id": "ip2lA1wjxqsf",
        "size": "678.5 K"
    },
    "A16版：广告.pdf": {
        "id": "ilFWm1wjxqxa",
        "size": "2.2 M"
    },
    "B01版：楼市周刊.pdf": {
        "id": "igwmK1wjxqwj",
        "size": "2.4 M"
    },
    "B02版：楼市·要闻.pdf": {
        "id": "iJ8X81wjxrgj",
        "size": "559.2 K"
    },
    "B03版：广告.pdf": {
        "id": "iwNWE1wjxreh",
        "size": "4.3 M"
    },
    "B04版：广告.pdf": {
        "id": "iy5jF1wjxquh",
        "size": "2.4 M"
    },
    "B05版：金融周刊.pdf": {
        "id": "idhOX1wjxrzi",
        "size": "1.5 M"
    },
    "B06版：理财.pdf": {
        "id": "i1kiT1wjxrad",
        "size": "453.7 K"
    },
    "B07版：专题.pdf": {
        "id": "iS6A81wjxrud",
        "size": "746.4 K"
    },
    "B08版：热点.pdf": {
        "id": "iZhKw1wjxrwf",
        "size": "1.4 M"
    }
}