{
    "A01版：头条要闻.pdf": {
        "id": "i458x1wscagf",
        "size": "1.1 M"
    },
    "A02版：城事.pdf": {
        "id": "iWl4E1wscahg",
        "size": "1.5 M"
    },
    "A03版：创文明城市 做文明市民.pdf": {
        "id": "ieQQp1wsca7g",
        "size": "1.4 M"
    },
    "A04版：那花 那树 那人.pdf": {
        "id": "i4D0f1wscaji",
        "size": "5.6 M"
    },
    "A05版：奋斗在鹰城.pdf": {
        "id": "iK5nK1wscaed",
        "size": "1.7 M"
    },
    "A06版：老年生活.pdf": {
        "id": "if62c1wscafe",
        "size": "1.4 M"
    },
    "A07版：小店故事.pdf": {
        "id": "iCHgs1wscadc",
        "size": "1.3 M"
    },
    "A08版：身边观察.pdf": {
        "id": "irizk1wsca8h",
        "size": "1.8 M"
    },
    "A09版：民生新闻.pdf": {
        "id": "iJ3iz1wscaba",
        "size": "1.3 M"
    },
    "A10版：时评.pdf": {
        "id": "iekTq1wsca5e",
        "size": "1.2 M"
    },
    "A11版：关注.pdf": {
        "id": "iLcND1wscaaj",
        "size": "1.1 M"
    },
    "A12版：国内.pdf": {
        "id": "iX6RM1wscacb",
        "size": "2.7 M"
    },
    "A13版：国际.pdf": {
        "id": "ih68n1wsca6f",
        "size": "4.2 M"
    },
    "A14版：体育.pdf": {
        "id": "i6ZBD1wscaih",
        "size": "1.0 M"
    },
    "A15版：公益广告.pdf": {
        "id": "iLAJI1wscakj",
        "size": "1.3 M"
    },
    "A16版：副刊.pdf": {
        "id": "iUjao1wsca9i",
        "size": "1.5 M"
    }
}