{
    "01版：头版.pdf": {
        "id": "iKVtx1wcricd",
        "size": "9.1 M"
    },
    "02版：要闻.pdf": {
        "id": "i9CfU1wcrhxi",
        "size": "2.1 M"
    },
    "03版：要闻.pdf": {
        "id": "ibM0z1wcripg",
        "size": "648.2 K"
    },
    "04版：天下.pdf": {
        "id": "iieu91wcriyf",
        "size": "7.8 M"
    },
    "05版：文化赣鄱.pdf": {
        "id": "iouP41wcrkud",
        "size": "6.5 M"
    },
    "06版：井冈山.pdf": {
        "id": "i07Bm1wcrkib",
        "size": "2.9 M"
    },
    "07版：读书.pdf": {
        "id": "iVy3Z1wcrimd",
        "size": "3.8 M"
    },
    "08版：品鉴.pdf": {
        "id": "ibC3T1wcrkad",
        "size": "7.0 M"
    },
    "T01版：牢记殷殷嘱托 书写精彩华章.pdf": {
        "id": "ijg3D1wcrk0d",
        "size": "12.0 M"
    },
    "T02版：牢记殷殷嘱托 书写精彩华章.pdf": {
        "id": "i3CD81wcrjpc",
        "size": "23.3 M"
    },
    "T03版：牢记殷殷嘱托 书写精彩华章.pdf": {
        "id": "imRsq1wcri3e",
        "size": "5.5 M"
    },
    "T04版：牢记殷殷嘱托 书写精彩华章.pdf": {
        "id": "iqBiC1wcrj4b",
        "size": "5.3 M"
    }
}