{
    "01版：要闻.pdf": {
        "id": "iRoMC1xm18wd",
        "size": "8.3 M"
    },
    "02版：要闻.pdf": {
        "id": "iTjM21xm18yf",
        "size": "4.5 M"
    },
    "03版：关注.pdf": {
        "id": "i2I321xm190h",
        "size": "20.2 M"
    },
    "04版：时事.pdf": {
        "id": "ioE0H1xm191i",
        "size": "4.0 M"
    },
    "05版：北海周末.pdf": {
        "id": "iwTC51xm196d",
        "size": "10.1 M"
    },
    "06版：潍水岸.pdf": {
        "id": "i6Oq21xm19ah",
        "size": "10.5 M"
    },
    "07版：十笏园.pdf": {
        "id": "iEBJP1xm19fc",
        "size": "5.6 M"
    },
    "08版：教育.pdf": {
        "id": "i5elc1xm19kh",
        "size": "20.1 M"
    }
}