{
    "A01版.pdf": {
        "id": "i5DHj203hlpe",
        "size": "319.4 K"
    },
    "A02版.pdf": {
        "id": "i2dqi203hm8d",
        "size": "729.5 K"
    },
    "A03版.pdf": {
        "id": "iyX2N203hmza",
        "size": "939.2 K"
    },
    "A04版.pdf": {
        "id": "iOtGN203hnne",
        "size": "631.8 K"
    },
    "A05版.pdf": {
        "id": "iIDWa203hore",
        "size": "824.6 K"
    },
    "A06版.pdf": {
        "id": "i8D9X203hpjc",
        "size": "830.1 K"
    },
    "A07版.pdf": {
        "id": "iKoSn203hqod",
        "size": "2.1 M"
    },
    "A08版.pdf": {
        "id": "i6XkR203hrni",
        "size": "915.2 K"
    },
    "A09版.pdf": {
        "id": "iNPOf203hsne",
        "size": "810.6 K"
    },
    "A10版.pdf": {
        "id": "iyDOc203htbi",
        "size": "1.3 M"
    },
    "A11版.pdf": {
        "id": "i90qA203htzc",
        "size": "765.6 K"
    },
    "A12版.pdf": {
        "id": "i0FXQ203hueh",
        "size": "804.6 K"
    },
    "A13版.pdf": {
        "id": "iUHuP203huve",
        "size": "839.8 K"
    },
    "A14版.pdf": {
        "id": "iSZLG203hvcb",
        "size": "749.9 K"
    },
    "A15版.pdf": {
        "id": "i6bDL203hwid",
        "size": "825.6 K"
    },
    "A16版.pdf": {
        "id": "isCoV203hxij",
        "size": "612.3 K"
    },
    "A17版.pdf": {
        "id": "isdXT203hy9g",
        "size": "773.7 K"
    },
    "A18版.pdf": {
        "id": "iV0kM203hz7a",
        "size": "759.2 K"
    },
    "A19版.pdf": {
        "id": "ij9nX203i01a",
        "size": "557.4 K"
    },
    "A20版.pdf": {
        "id": "iYMhu203i0mb",
        "size": "585.1 K"
    },
    "A21版.pdf": {
        "id": "igTFx203i1je",
        "size": "1.0 M"
    },
    "A22版.pdf": {
        "id": "ij84E203i2ij",
        "size": "1.0 M"
    },
    "A23版.pdf": {
        "id": "irPOS203i38f",
        "size": "702.9 K"
    },
    "A24版.pdf": {
        "id": "ivGJV203i3uh",
        "size": "676.1 K"
    },
    "A25版.pdf": {
        "id": "ig7xg203i4jc",
        "size": "809.7 K"
    },
    "A26版.pdf": {
        "id": "igGtW203i51a",
        "size": "827.1 K"
    },
    "A27版.pdf": {
        "id": "ivwBz203i5kj",
        "size": "1.2 M"
    },
    "A28版.pdf": {
        "id": "iiH0l203i69e",
        "size": "694.0 K"
    },
    "A29版.pdf": {
        "id": "iWrgq203i74f",
        "size": "2.3 M"
    },
    "A30版.pdf": {
        "id": "iELFF203i8cj",
        "size": "731.5 K"
    },
    "A31版.pdf": {
        "id": "ihrDR203i95i",
        "size": "845.0 K"
    },
    "A32版.pdf": {
        "id": "iQIGj203i9qj",
        "size": "1.2 M"
    },
    "A33版.pdf": {
        "id": "iX6M1203iagf",
        "size": "932.0 K"
    },
    "A34版.pdf": {
        "id": "icz3n203ibch",
        "size": "831.3 K"
    },
    "A35版.pdf": {
        "id": "ip4qd203ickb",
        "size": "938.9 K"
    },
    "A36版.pdf": {
        "id": "icNym203idre",
        "size": "921.0 K"
    },
    "B01版.pdf": {
        "id": "iAQHc203ietc",
        "size": "593.2 K"
    },
    "B02版.pdf": {
        "id": "ibVhq203iffe",
        "size": "560.6 K"
    },
    "B03版.pdf": {
        "id": "iQ5h1203igaf",
        "size": "517.4 K"
    },
    "B04版.pdf": {
        "id": "iGA4X203igsd",
        "size": "768.8 K"
    },
    "B05版.pdf": {
        "id": "iIINc203ihcd",
        "size": "1.3 M"
    },
    "B06版.pdf": {
        "id": "iPCwg203ii6d",
        "size": "935.4 K"
    },
    "B07版.pdf": {
        "id": "idSWS203ij5i",
        "size": "657.7 K"
    },
    "B08版.pdf": {
        "id": "i7N7v203ik0j",
        "size": "738.2 K"
    },
    "C01版.pdf": {
        "id": "iEX3U203ikpe",
        "size": "1,012.2 K"
    },
    "C02版.pdf": {
        "id": "iAMzm203ilsd",
        "size": "3.0 M"
    },
    "C03版.pdf": {
        "id": "ipWzE203imwd",
        "size": "5.2 M"
    },
    "C04版.pdf": {
        "id": "iu53S203inob",
        "size": "737.9 K"
    }
}