{
    "A001版：头版.pdf": {
        "id": "iQvnF234lrkd",
        "size": "487.4 K"
    },
    "A002版：综合.pdf": {
        "id": "ideM7234ls1a",
        "size": "448.1 K"
    },
    "A003版：市场.pdf": {
        "id": "ienFL234lskj",
        "size": "519.0 K"
    },
    "A004版：公司.pdf": {
        "id": "iyUwL234lt0f",
        "size": "639.5 K"
    },
    "B001版：信息披露.pdf": {
        "id": "ifrLC234ltfa",
        "size": "460.9 K"
    },
    "B002版：信息披露.pdf": {
        "id": "iv4nD234ltsd",
        "size": "499.1 K"
    },
    "B003版：信息披露.pdf": {
        "id": "ilXPH234ltyj",
        "size": "488.0 K"
    },
    "B004版：信息披露.pdf": {
        "id": "iaMam234lu8j",
        "size": "401.3 K"
    },
    "B005版：信息披露.pdf": {
        "id": "iPp0O234lugh",
        "size": "388.0 K"
    },
    "B006版：信息披露.pdf": {
        "id": "inbKR234luri",
        "size": "470.8 K"
    },
    "B007版：信息披露.pdf": {
        "id": "ia83q234lv2j",
        "size": "442.6 K"
    },
    "B008版：信息披露.pdf": {
        "id": "iMAev234lvbi",
        "size": "437.1 K"
    },
    "B009版：信息披露.pdf": {
        "id": "iT6rk234lvjg",
        "size": "454.0 K"
    },
    "B010版：信息披露.pdf": {
        "id": "iKEKh234lvre",
        "size": "450.0 K"
    },
    "B011版：信息披露.pdf": {
        "id": "is4vg234lvyb",
        "size": "387.1 K"
    },
    "B012版：信息披露.pdf": {
        "id": "ii1oJ234lw8b",
        "size": "438.8 K"
    },
    "B013版：信息披露.pdf": {
        "id": "i8qqw234lwjc",
        "size": "387.5 K"
    },
    "B014版：信息披露.pdf": {
        "id": "icpF4234lwxg",
        "size": "405.8 K"
    },
    "B015版：信息披露.pdf": {
        "id": "iO3H0234lxaj",
        "size": "422.7 K"
    },
    "B016版：信息披露.pdf": {
        "id": "iY0uB234lxnc",
        "size": "398.9 K"
    },
    "B017版：信息披露.pdf": {
        "id": "iu1Z2234ly1g",
        "size": "428.2 K"
    },
    "B018版：信息披露.pdf": {
        "id": "ityyG234lyhc",
        "size": "422.4 K"
    },
    "B019版：信息披露.pdf": {
        "id": "iZBk6234lyza",
        "size": "445.4 K"
    },
    "B020版：信息披露.pdf": {
        "id": "iOSGw234lz7i",
        "size": "422.0 K"
    },
    "B021版：信息披露.pdf": {
        "id": "iMtqf234lzkb",
        "size": "414.5 K"
    },
    "B022版：信息披露.pdf": {
        "id": "ihr33234lzwd",
        "size": "434.2 K"
    },
    "B023版：信息披露.pdf": {
        "id": "iEZp5234m0cj",
        "size": "433.5 K"
    },
    "B024版：信息披露.pdf": {
        "id": "iEAfI234m0qd",
        "size": "426.1 K"
    },
    "B025版：信息披露.pdf": {
        "id": "iempO234m13g",
        "size": "431.0 K"
    },
    "B026版：信息披露.pdf": {
        "id": "i1ys8234m1jc",
        "size": "425.0 K"
    },
    "B027版：信息披露.pdf": {
        "id": "iTSUi234m22b",
        "size": "453.2 K"
    },
    "B028版：信息披露.pdf": {
        "id": "i69zS234m2hg",
        "size": "440.8 K"
    },
    "B029版：信息披露.pdf": {
        "id": "iD0i5234m2ti",
        "size": "435.1 K"
    },
    "B030版：信息披露.pdf": {
        "id": "io3gL234m37c",
        "size": "412.9 K"
    },
    "B031版：信息披露.pdf": {
        "id": "ihVh8234m3je",
        "size": "408.8 K"
    },
    "B032版：信息披露.pdf": {
        "id": "iArZO234m3vg",
        "size": "417.5 K"
    },
    "B033版：信息披露.pdf": {
        "id": "iRHRd234m47i",
        "size": "454.1 K"
    },
    "B034版：信息披露.pdf": {
        "id": "iIa1M234m4of",
        "size": "463.5 K"
    },
    "B035版：信息披露.pdf": {
        "id": "iVS3Y234m57e",
        "size": "441.1 K"
    },
    "B036版：信息披露.pdf": {
        "id": "ie2Ty234m5kh",
        "size": "401.5 K"
    },
    "B037版：信息披露.pdf": {
        "id": "iUgxP234m5xa",
        "size": "468.2 K"
    },
    "B038版：信息披露.pdf": {
        "id": "iiLxd234m63g",
        "size": "422.5 K"
    },
    "B039版：信息披露.pdf": {
        "id": "igXnq234m6eh",
        "size": "434.8 K"
    },
    "B040版：信息披露.pdf": {
        "id": "ig4Km234m6ud",
        "size": "457.8 K"
    },
    "B041版：信息披露.pdf": {
        "id": "i8L4P234m7cb",
        "size": "449.2 K"
    },
    "B042版：信息披露.pdf": {
        "id": "iUZuF234m7uj",
        "size": "376.7 K"
    },
    "B043版：信息披露.pdf": {
        "id": "izWxG234m8fa",
        "size": "422.5 K"
    },
    "B044版：信息披露.pdf": {
        "id": "iQ6Im234m8vg",
        "size": "389.9 K"
    },
    "B045版：信息披露.pdf": {
        "id": "i6BaW234m94f",
        "size": "393.6 K"
    },
    "B046版：信息披露.pdf": {
        "id": "iMjB2234m9bc",
        "size": "447.5 K"
    },
    "B047版：信息披露.pdf": {
        "id": "i8TRM234m9ij",
        "size": "459.9 K"
    },
    "B048版：信息披露.pdf": {
        "id": "ipEmN234m9wd",
        "size": "481.5 K"
    },
    "B049版：信息披露.pdf": {
        "id": "iz2za234ma8f",
        "size": "447.2 K"
    },
    "B050版：信息披露.pdf": {
        "id": "iyE6S234mana",
        "size": "457.0 K"
    },
    "B051版：信息披露.pdf": {
        "id": "iNVqV234mb1e",
        "size": "398.4 K"
    },
    "B052版：信息披露.pdf": {
        "id": "izyuB234mbdg",
        "size": "397.7 K"
    },
    "B053版：信息披露.pdf": {
        "id": "iJdA7234mbra",
        "size": "434.9 K"
    },
    "B054版：信息披露.pdf": {
        "id": "iLPud234mc0j",
        "size": "415.3 K"
    },
    "B055版：信息披露.pdf": {
        "id": "i1vPV234mcdc",
        "size": "463.1 K"
    },
    "B056版：信息披露.pdf": {
        "id": "iHxh0234mcuj",
        "size": "376.7 K"
    },
    "B057版：信息披露.pdf": {
        "id": "iBvO9234md5a",
        "size": "436.8 K"
    },
    "B058版：信息披露.pdf": {
        "id": "iv3NV234mdid",
        "size": "419.4 K"
    },
    "B059版：信息披露.pdf": {
        "id": "i46eF234me0b",
        "size": "400.1 K"
    },
    "B060版：信息披露.pdf": {
        "id": "iTsGP234meef",
        "size": "431.5 K"
    },
    "B061版：信息披露.pdf": {
        "id": "imHuu234meqh",
        "size": "371.8 K"
    },
    "B062版：信息披露.pdf": {
        "id": "ikNn4234mf0h",
        "size": "429.0 K"
    },
    "B063版：信息披露.pdf": {
        "id": "iPc8h234mfah",
        "size": "423.6 K"
    },
    "B064版：信息披露.pdf": {
        "id": "iC9hk234mfqd",
        "size": "453.9 K"
    },
    "B065版：信息披露.pdf": {
        "id": "iP7xK234mg3g",
        "size": "493.4 K"
    },
    "B066版：信息披露.pdf": {
        "id": "imJLO234mgjc",
        "size": "385.1 K"
    },
    "B067版：信息披露.pdf": {
        "id": "iCU8h234mgud",
        "size": "458.5 K"
    },
    "B068版：信息披露.pdf": {
        "id": "ig4pz234mhih",
        "size": "477.7 K"
    },
    "B069版：信息披露.pdf": {
        "id": "iOHgu234mi2h",
        "size": "455.0 K"
    },
    "B070版：信息披露.pdf": {
        "id": "iDUkn234mikf",
        "size": "395.5 K"
    },
    "B071版：信息披露.pdf": {
        "id": "iuoip234mj6h",
        "size": "404.1 K"
    },
    "B072版：信息披露.pdf": {
        "id": "iGEcN234mjri",
        "size": "425.7 K"
    },
    "B073版：信息披露.pdf": {
        "id": "i2EW3234mkah",
        "size": "377.3 K"
    },
    "B074版：信息披露.pdf": {
        "id": "iNDUE234mkmj",
        "size": "405.3 K"
    },
    "B075版：信息披露.pdf": {
        "id": "iynCm234ml1e",
        "size": "430.1 K"
    },
    "B076版：信息披露.pdf": {
        "id": "iMdqr234mlha",
        "size": "407.7 K"
    },
    "B077版：信息披露.pdf": {
        "id": "iNyrw234mlve",
        "size": "419.3 K"
    },
    "B078版：信息披露.pdf": {
        "id": "ilBol234mm5e",
        "size": "414.8 K"
    },
    "B079版：信息披露.pdf": {
        "id": "iZgrD234mmkj",
        "size": "456.8 K"
    },
    "B080版：信息披露.pdf": {
        "id": "i7i9h234mmwb",
        "size": "397.1 K"
    },
    "B081版：信息披露.pdf": {
        "id": "iOXrj234mn8d",
        "size": "399.9 K"
    },
    "B082版：信息披露.pdf": {
        "id": "iicKe234mnje",
        "size": "430.4 K"
    },
    "B083版：信息披露.pdf": {
        "id": "iFX0r234mnvg",
        "size": "454.5 K"
    },
    "B084版：信息披露.pdf": {
        "id": "iWPqh234mo4f",
        "size": "429.6 K"
    },
    "B085版：信息披露.pdf": {
        "id": "iEVdk234moef",
        "size": "428.0 K"
    },
    "B086版：信息披露.pdf": {
        "id": "ieB0X234momd",
        "size": "429.4 K"
    },
    "B087版：信息披露.pdf": {
        "id": "iTXWE234moub",
        "size": "378.9 K"
    },
    "B088版：信息披露.pdf": {
        "id": "iCYvx234mp4b",
        "size": "424.6 K"
    },
    "B089版：信息披露.pdf": {
        "id": "iyRHI234mpjg",
        "size": "447.3 K"
    },
    "B090版：信息披露.pdf": {
        "id": "izsWw234mpsf",
        "size": "432.4 K"
    },
    "B091版：信息披露.pdf": {
        "id": "izyQt234mq1e",
        "size": "428.9 K"
    },
    "B092版：信息披露.pdf": {
        "id": "iPqA0234mqib",
        "size": "427.1 K"
    },
    "B093版：信息披露.pdf": {
        "id": "iq714234mqxg",
        "size": "495.1 K"
    },
    "B094版：信息披露.pdf": {
        "id": "iBI9J234mr5e",
        "size": "453.2 K"
    },
    "B095版：信息披露.pdf": {
        "id": "iFjH4234mrgf",
        "size": "441.0 K"
    },
    "B096版：信息披露.pdf": {
        "id": "iHWIF234mrqf",
        "size": "400.3 K"
    },
    "B097版：信息披露.pdf": {
        "id": "iLGci234mryd",
        "size": "520.3 K"
    },
    "B098版：信息披露.pdf": {
        "id": "igyUm234ms6b",
        "size": "471.2 K"
    },
    "B099版：信息披露.pdf": {
        "id": "iKsIA234msid",
        "size": "489.1 K"
    },
    "B100版：信息披露.pdf": {
        "id": "iqlMi234msuf",
        "size": "462.4 K"
    },
    "B101版：信息披露.pdf": {
        "id": "ihhwc234mt0b",
        "size": "453.6 K"
    },
    "B102版：信息披露.pdf": {
        "id": "iQfJJ234mt7i",
        "size": "428.4 K"
    },
    "B103版：信息披露.pdf": {
        "id": "iS10x234mthi",
        "size": "514.0 K"
    },
    "B104版：信息披露.pdf": {
        "id": "iNrcI234mtxe",
        "size": "522.3 K"
    },
    "B105版：信息披露.pdf": {
        "id": "i7c8R234mu3a",
        "size": "451.1 K"
    },
    "B106版：信息披露.pdf": {
        "id": "ib8AS234mubi",
        "size": "424.2 K"
    },
    "B107版：信息披露.pdf": {
        "id": "ihRBo234muqd",
        "size": "479.9 K"
    },
    "B108版：信息披露.pdf": {
        "id": "i6wVG234mv3g",
        "size": "480.0 K"
    },
    "B109版：信息披露.pdf": {
        "id": "ijHjf234mvbe",
        "size": "444.9 K"
    },
    "B110版：信息披露.pdf": {
        "id": "ijcnp234mvkd",
        "size": "430.6 K"
    },
    "B111版：信息披露.pdf": {
        "id": "i99Fa234mvsb",
        "size": "440.0 K"
    },
    "B112版：信息披露.pdf": {
        "id": "iEwYx234mvzi",
        "size": "447.5 K"
    },
    "B113版：信息披露.pdf": {
        "id": "im1Vb234mw6f",
        "size": "415.8 K"
    },
    "B114版：信息披露.pdf": {
        "id": "ilVg4234mwgf",
        "size": "391.3 K"
    },
    "B115版：信息披露.pdf": {
        "id": "ipniT234mwod",
        "size": "369.7 K"
    },
    "B116版：信息披露.pdf": {
        "id": "iEDhY234mwti",
        "size": "402.5 K"
    },
    "B117版：信息披露.pdf": {
        "id": "iQnku234mx2h",
        "size": "413.6 K"
    },
    "B118版：信息披露.pdf": {
        "id": "i5XYg234mxch",
        "size": "500.3 K"
    },
    "B119版：信息披露.pdf": {
        "id": "iocYv234mxni",
        "size": "401.2 K"
    },
    "B120版：信息披露.pdf": {
        "id": "i2rVH234mxxi",
        "size": "438.0 K"
    },
    "B121版：信息披露.pdf": {
        "id": "iZFzJ234my7i",
        "size": "529.4 K"
    },
    "B122版：信息披露.pdf": {
        "id": "i89F5234mymd",
        "size": "386.2 K"
    },
    "B123版：信息披露.pdf": {
        "id": "i8qzq234mywd",
        "size": "393.5 K"
    },
    "B124版：信息披露.pdf": {
        "id": "icYu7234mz7e",
        "size": "442.8 K"
    },
    "B125版：信息披露.pdf": {
        "id": "i7Zoh234mzeb",
        "size": "385.2 K"
    },
    "B126版：信息披露.pdf": {
        "id": "i5bl8234mzqd",
        "size": "421.6 K"
    },
    "B127版：信息披露.pdf": {
        "id": "ijEZi234n02f",
        "size": "418.3 K"
    },
    "B128版：信息披露.pdf": {
        "id": "i4dkR234n0cf",
        "size": "454.3 K"
    },
    "B129版：信息披露.pdf": {
        "id": "ipS1Y234n0jc",
        "size": "428.3 K"
    },
    "B130版：信息披露.pdf": {
        "id": "idKM6234n0ra",
        "size": "444.1 K"
    },
    "B131版：信息披露.pdf": {
        "id": "ipFVJ234n12b",
        "size": "426.4 K"
    },
    "B132版：信息披露.pdf": {
        "id": "iSjA2234n1cb",
        "size": "436.4 K"
    },
    "B133版：信息披露.pdf": {
        "id": "iEUd8234n1od",
        "size": "393.8 K"
    },
    "B134版：信息披露.pdf": {
        "id": "ihHMZ234n27c",
        "size": "553.6 K"
    },
    "B135版：信息披露.pdf": {
        "id": "iel2l234n2gb",
        "size": "516.6 K"
    },
    "B136版：信息披露.pdf": {
        "id": "inXrQ234n2oj",
        "size": "478.5 K"
    },
    "B137版：信息披露.pdf": {
        "id": "iPvQp234n2yj",
        "size": "363.5 K"
    },
    "B138版：信息披露.pdf": {
        "id": "iVTcn234n38j",
        "size": "396.4 K"
    },
    "B139版：信息披露.pdf": {
        "id": "izAva234n3hi",
        "size": "398.2 K"
    },
    "B140版：信息披露.pdf": {
        "id": "ilu3h234n3pg",
        "size": "358.5 K"
    },
    "B141版：信息披露.pdf": {
        "id": "iOkIc234n45c",
        "size": "455.6 K"
    },
    "B142版：信息披露.pdf": {
        "id": "iH1kK234n4kh",
        "size": "473.0 K"
    },
    "B143版：信息披露.pdf": {
        "id": "iIsTI234n51e",
        "size": "393.4 K"
    },
    "B144版：信息披露.pdf": {
        "id": "iq8wa234n5eh",
        "size": "427.3 K"
    },
    "B145版：信息披露.pdf": {
        "id": "i66Ph234n5pi",
        "size": "450.4 K"
    },
    "B146版：信息披露.pdf": {
        "id": "ietUI234n5zi",
        "size": "437.8 K"
    },
    "B147版：信息披露.pdf": {
        "id": "ix9eg234n67g",
        "size": "435.8 K"
    },
    "B148版：信息披露.pdf": {
        "id": "iDgEA234n6ji",
        "size": "401.1 K"
    },
    "B149版：信息披露.pdf": {
        "id": "ia3I8234n6rg",
        "size": "513.1 K"
    },
    "B150版：信息披露.pdf": {
        "id": "iT6FD234n6ze",
        "size": "486.1 K"
    },
    "B151版：信息披露.pdf": {
        "id": "idXbE234n79e",
        "size": "453.4 K"
    },
    "B152版：信息披露.pdf": {
        "id": "ivyh1234n7id",
        "size": "509.2 K"
    },
    "B153版：信息披露.pdf": {
        "id": "i18XO234n7sd",
        "size": "456.3 K"
    },
    "B154版：信息披露.pdf": {
        "id": "iasks234n81c",
        "size": "433.5 K"
    },
    "B155版：信息披露.pdf": {
        "id": "iKB16234n8gh",
        "size": "460.4 K"
    },
    "B156版：信息披露.pdf": {
        "id": "iuXHy234n8ub",
        "size": "426.1 K"
    },
    "B157版：信息披露.pdf": {
        "id": "iBpCE234n97e",
        "size": "429.2 K"
    },
    "B158版：信息披露.pdf": {
        "id": "iZw0S234n9pc",
        "size": "456.8 K"
    },
    "B159版：信息披露.pdf": {
        "id": "iwo7f234na0d",
        "size": "429.3 K"
    },
    "B160版：信息披露.pdf": {
        "id": "iaIXt234naad",
        "size": "350.6 K"
    },
    "B161版：信息披露.pdf": {
        "id": "i6Ast234najc",
        "size": "496.6 K"
    },
    "B162版：信息披露.pdf": {
        "id": "iPtXG234nasb",
        "size": "466.1 K"
    },
    "B163版：信息披露.pdf": {
        "id": "ipPTp234nb2b",
        "size": "449.3 K"
    },
    "B164版：信息披露.pdf": {
        "id": "iZ4At234nbdc",
        "size": "450.9 K"
    },
    "B165版：信息披露.pdf": {
        "id": "ikvEv234nbwb",
        "size": "490.4 K"
    },
    "B166版：信息披露.pdf": {
        "id": "ieSrz234ncdi",
        "size": "454.9 K"
    },
    "B167版：信息披露.pdf": {
        "id": "icKiO234ncrc",
        "size": "529.1 K"
    },
    "B168版：信息披露.pdf": {
        "id": "i1ax4234nd0b",
        "size": "413.0 K"
    },
    "B169版：信息披露.pdf": {
        "id": "ip6XM234ndfg",
        "size": "409.4 K"
    },
    "B170版：信息披露.pdf": {
        "id": "iyTof234ndof",
        "size": "426.0 K"
    },
    "B171版：信息披露.pdf": {
        "id": "i4gKp234ndzg",
        "size": "383.3 K"
    },
    "B172版：信息披露.pdf": {
        "id": "iMlB3234ne8f",
        "size": "426.5 K"
    }
}