{
    "A01版：头版.pdf": {
        "id": "iUqEC1zqbfqf",
        "size": "3.4 M"
    },
    "A02版：要闻.pdf": {
        "id": "i9Rdq1zqbg3i",
        "size": "1.9 M"
    },
    "A03版：让好人上头条.pdf": {
        "id": "ixWJg1zqbgfa",
        "size": "1.4 M"
    },
    "A04版：青海·关注.pdf": {
        "id": "iibNo1zqbgyj",
        "size": "2.4 M"
    },
    "A05版：财经观察.pdf": {
        "id": "iL9lc1zqbhne",
        "size": "2.8 M"
    },
    "A06版：社区·记者帮.pdf": {
        "id": "iFzhT1zqbi7e",
        "size": "3.2 M"
    },
    "A07版：青海·综合.pdf": {
        "id": "iPh461zqbikh",
        "size": "1.7 M"
    },
    "A08版：海北新闻.pdf": {
        "id": "iM5TT1zqbj4h",
        "size": "3.5 M"
    },
    "A09版：中国·聚焦.pdf": {
        "id": "io0tF1zqbjle",
        "size": "1.6 M"
    },
    "A10版：中国·图解.pdf": {
        "id": "ifUhv1zqbk6f",
        "size": "734.6 K"
    },
    "A11版：中国·万象.pdf": {
        "id": "i5Nkl1zqbkkj",
        "size": "1,019.9 K"
    },
    "A12版：体育·综合.pdf": {
        "id": "ijWVQ1zqbl2h",
        "size": "3.3 M"
    },
    "A13版：体彩·资讯.pdf": {
        "id": "iLbgU1zqbloj",
        "size": "3.4 M"
    },
    "A14版：天下·关注.pdf": {
        "id": "i4OSS1zqbmcd",
        "size": "2.3 M"
    },
    "A15版：天下·关注.pdf": {
        "id": "iHuEo1zqbmvc",
        "size": "1.1 M"
    },
    "A16版：天下·关注.pdf": {
        "id": "iaJeO1zqbnqd",
        "size": "3.5 M"
    }
}