{
    "A01版：头版.pdf": {
        "id": "iqo3n29z4mwf",
        "size": "1.7 M"
    },
    "A02版：社论·来信.pdf": {
        "id": "iKUoS29z4n2b",
        "size": "598.3 K"
    },
    "A03版：调查·评论.pdf": {
        "id": "ilXuI29z4ncb",
        "size": "595.2 K"
    },
    "A04版：要闻.pdf": {
        "id": "i2ZNe29z4ngf",
        "size": "740.8 K"
    },
    "A05版：封面报道.pdf": {
        "id": "iRWaH29z4nkj",
        "size": "681.2 K"
    },
    "A06版：封面报道.pdf": {
        "id": "i4sUd29z4nod",
        "size": "1.1 M"
    },
    "A07版：封面报道.pdf": {
        "id": "iH9NU29z4nuj",
        "size": "900.6 K"
    },
    "A08版：封面报道.pdf": {
        "id": "ipCzF29z4nxc",
        "size": "580.3 K"
    },
    "A09版：热点.pdf": {
        "id": "iij1z29z4o1g",
        "size": "582.9 K"
    },
    "A10版：北京新闻·城事.pdf": {
        "id": "iNe6g29z4o2h",
        "size": "833.0 K"
    },
    "A11版：城事.pdf": {
        "id": "iQzrh29z4o8d",
        "size": "870.9 K"
    },
    "A12版：城事.pdf": {
        "id": "iHbAT29z4odi",
        "size": "847.5 K"
    },
    "A13版：拍案.pdf": {
        "id": "iUWIM29z4ogb",
        "size": "602.6 K"
    },
    "A14版：中国新闻·时事.pdf": {
        "id": "iRROl29z4oje",
        "size": "479.2 K"
    },
    "A15版：时事.pdf": {
        "id": "ig4ts29z4olg",
        "size": "690.7 K"
    },
    "A16版：国际新闻·天下.pdf": {
        "id": "isaAx29z4orc",
        "size": "955.5 K"
    },
    "A17版：经济新闻·投资.pdf": {
        "id": "i7VAF29z4ote",
        "size": "543.0 K"
    },
    "A18版：公司.pdf": {
        "id": "iIMku29z4oxi",
        "size": "856.3 K"
    },
    "A19版：文娱新闻·现场.pdf": {
        "id": "iG3KQ29z4p2d",
        "size": "1,004.2 K"
    },
    "A20版：表情.pdf": {
        "id": "iqHyW29z4p7i",
        "size": "1.3 M"
    },
    "A21版：体育新闻·看台.pdf": {
        "id": "i09e829z4pab",
        "size": "663.3 K"
    },
    "A22版：幕后.pdf": {
        "id": "i02yA29z4pgh",
        "size": "666.6 K"
    },
    "A23版：气象.pdf": {
        "id": "iaYT729z4pkb",
        "size": "865.9 K"
    },
    "A24版：广告.pdf": {
        "id": "ip0DJ29z4pta",
        "size": "986.7 K"
    },
    "B01版：书评周刊.pdf": {
        "id": "iqZQC29z4pyf",
        "size": "1.3 M"
    },
    "B02版：书评周刊·主题.pdf": {
        "id": "iAsdN29z4q3a",
        "size": "710.9 K"
    },
    "B03版：书评周刊·主题.pdf": {
        "id": "iWAJo29z4q7e",
        "size": "657.1 K"
    },
    "B04版：书评周刊·对话.pdf": {
        "id": "iYC6Q29z4qbi",
        "size": "783.8 K"
    },
    "B05版：书评周刊·艺术.pdf": {
        "id": "iK86r29z4qda",
        "size": "622.7 K"
    },
    "B06版：书评周刊·写作.pdf": {
        "id": "i0fQg29z4qif",
        "size": "720.4 K"
    },
    "B07版：书评周刊·社科.pdf": {
        "id": "iLXL829z4qna",
        "size": "802.7 K"
    },
    "B08版_B09版：书评周刊·短书评·书情.pdf": {
        "id": "iJXpt29z4qtg",
        "size": "817.5 K"
    },
    "B10版：书评周刊·畅销.pdf": {
        "id": "iQfyu29z4qzc",
        "size": "764.6 K"
    },
    "B11版：书评周刊·职人.pdf": {
        "id": "i21lK29z4r7a",
        "size": "566.2 K"
    },
    "B12版_B13版：书评周刊·历史.pdf": {
        "id": "iAMS229z4rdg",
        "size": "1.3 M"
    },
    "B14版：书评周刊·新知.pdf": {
        "id": "iuThc29z4rgj",
        "size": "558.8 K"
    },
    "B15版：书评周刊·书单.pdf": {
        "id": "isEEL29z4rha",
        "size": "619.7 K"
    },
    "B16版：书评周刊·排行榜.pdf": {
        "id": "ioFcu29z4rle",
        "size": "554.1 K"
    }
}