{
    "A01版：奧運專版.pdf": {
        "id": "iARZF1v18wwb",
        "size": "1.7 M"
    },
    "A02版：要聞.pdf": {
        "id": "iFBlY1v18wze",
        "size": "1.0 M"
    },
    "A03版：要聞.pdf": {
        "id": "iGBbD1v18x1g",
        "size": "1.3 M"
    },
    "A04版：要聞.pdf": {
        "id": "ifGIo1v18x3i",
        "size": "1.1 M"
    },
    "A05版：盛世華人系列.pdf": {
        "id": "iVMyF1v18x5a",
        "size": "1.7 M"
    },
    "A06版：京奧08.pdf": {
        "id": "i9q4B1v18x7c",
        "size": "916.7 K"
    },
    "A07版：港聞.pdf": {
        "id": "iP2xI1v18x8d",
        "size": "555.2 K"
    },
    "A08版：教育.pdf": {
        "id": "iwS5T1v18xaf",
        "size": "1.8 M"
    },
    "A09版：港聞.pdf": {
        "id": "iOT271v18xch",
        "size": "728.3 K"
    },
    "A10版：港聞.pdf": {
        "id": "iFIhp1v18xej",
        "size": "1.4 M"
    },
    "A11版：港聞.pdf": {
        "id": "iPPH61v18xgb",
        "size": "1.3 M"
    },
    "A12版：港聞.pdf": {
        "id": "i7Yyo1v18xid",
        "size": "1.6 M"
    },
    "A13版：京奧08.pdf": {
        "id": "ilyqn1v18xlg",
        "size": "1.3 M"
    },
    "A14版：京奧08.pdf": {
        "id": "itUtH1v18xni",
        "size": "881.9 K"
    },
    "A15版：京奧08.pdf": {
        "id": "i90Y81v18xpa",
        "size": "1.4 M"
    },
    "A16版：海峽兩岸·海西專版.pdf": {
        "id": "idV2p1v18xrc",
        "size": "766.1 K"
    },
    "A17版：台灣新聞.pdf": {
        "id": "i5ZrF1v18xte",
        "size": "1.3 M"
    },
    "A18版：大公評論.pdf": {
        "id": "ightI1v18xvg",
        "size": "905.3 K"
    },
    "A19版：大公評論.pdf": {
        "id": "i1G3R1v18xyj",
        "size": "914.2 K"
    },
    "A20版：中國新聞.pdf": {
        "id": "iY9r11v18xza",
        "size": "1.2 M"
    },
    "A21版：港聞.pdf": {
        "id": "iJNs41v18y1c",
        "size": "1,002.6 K"
    },
    "A22版：世界新潮.pdf": {
        "id": "iRBP51v18y3e",
        "size": "1.1 M"
    },
    "A23版：國際新聞.pdf": {
        "id": "ibfUv1v18y5g",
        "size": "900.3 K"
    },
    "A24版：國際新聞.pdf": {
        "id": "izSbh1v18y7i",
        "size": "1.3 M"
    },
    "A25版：京奧08.pdf": {
        "id": "i5usW1v18y8j",
        "size": "1.1 M"
    },
    "A26版：京奧08.pdf": {
        "id": "iAWIX1v18yab",
        "size": "1.9 M"
    },
    "A27版：專版.pdf": {
        "id": "i1IOS1v18ycd",
        "size": "1.4 M"
    },
    "A28版：中華醫藥.pdf": {
        "id": "iJKYE1v18yef",
        "size": "1.4 M"
    },
    "A29版：廣告.pdf": {
        "id": "iiix31v18yfg",
        "size": "712.8 K"
    },
    "A30版：體育.pdf": {
        "id": "ixgrN1v18yij",
        "size": "1.9 M"
    },
    "A31版：京奧08.pdf": {
        "id": "iCL1z1v18ykb",
        "size": "1.9 M"
    },
    "A32版：京奧08.pdf": {
        "id": "iZwKD1v18ymd",
        "size": "2.2 M"
    },
    "B01版：大公經濟.pdf": {
        "id": "iOXU81v18yof",
        "size": "903.2 K"
    },
    "B02版：香港經濟.pdf": {
        "id": "iXuvw1v18yqh",
        "size": "1.3 M"
    },
    "B03版：國際經濟.pdf": {
        "id": "i5LvR1v18ysj",
        "size": "1.4 M"
    },
    "B04版：投資全方位.pdf": {
        "id": "inWIa1v18yub",
        "size": "925.8 K"
    },
    "B08版：地產.pdf": {
        "id": "ikCmN1v18yvc",
        "size": "942.2 K"
    },
    "B09版：物流與航運.pdf": {
        "id": "iZCOV1v18yxe",
        "size": "855.3 K"
    },
    "B10版：社團新訊.pdf": {
        "id": "iul3H1v18yzg",
        "size": "1.8 M"
    },
    "B11版：中國證券.pdf": {
        "id": "iEetK1v18z2j",
        "size": "846.0 K"
    },
    "B12版：中國經濟.pdf": {
        "id": "ix7yX1v18z4b",
        "size": "1,023.0 K"
    },
    "C01版：娛樂.pdf": {
        "id": "iPHjY1v18z6d",
        "size": "1.1 M"
    },
    "C02版：娛樂.pdf": {
        "id": "i1sQQ1v18z7e",
        "size": "2.0 M"
    },
    "C03版：娛樂.pdf": {
        "id": "iZCil1v18z8f",
        "size": "2.4 M"
    },
    "C04版：陝西新聞.pdf": {
        "id": "iNnyh1v18z9g",
        "size": "828.3 K"
    },
    "C05版：大公園.pdf": {
        "id": "iaGCO1v18zcj",
        "size": "965.4 K"
    },
    "C06版：新園地.pdf": {
        "id": "i26HA1v18zeb",
        "size": "1.5 M"
    },
    "C07版：工商資訊.pdf": {
        "id": "ipurK1v18zfc",
        "size": "1.3 M"
    },
    "C08版：文化.pdf": {
        "id": "i1eAE1v18zhe",
        "size": "2.4 M"
    },
    "C09版：娛樂.pdf": {
        "id": "iikcJ1v18zif",
        "size": "882.5 K"
    },
    "C10版：娛樂.pdf": {
        "id": "icI281v18zli",
        "size": "1.6 M"
    }
}