{
    "01版：要闻.pdf": {
        "id": "iS9ON1wfs4sj",
        "size": "1.6 M"
    },
    "02版：要闻.pdf": {
        "id": "iUeXQ1wfs58f",
        "size": "2.1 M"
    },
    "03版：国内.pdf": {
        "id": "itZCU1wfs5cj",
        "size": "689.1 K"
    },
    "04版：专题.pdf": {
        "id": "ikMI81wfs5bi",
        "size": "2.9 M"
    },
    "05版：焦点·广告.pdf": {
        "id": "ix6261wfs4wd",
        "size": "1.1 M"
    },
    "06版：上海·专题.pdf": {
        "id": "iLyMM1wfs51i",
        "size": "2.9 M"
    },
    "07版：上海·专题.pdf": {
        "id": "iKpSj1wfs56d",
        "size": "2.7 M"
    },
    "08版：国际·专题.pdf": {
        "id": "iAGr81wfs4pg",
        "size": "1.4 M"
    },
    "09版：长三角周刊.pdf": {
        "id": "ilaY01wfs54b",
        "size": "3.3 M"
    },
    "10版：长三角·一体化.pdf": {
        "id": "iMxoI1wfs4ub",
        "size": "1.9 M"
    },
    "11版：长三角·最江南.pdf": {
        "id": "iLPMh1wfs52j",
        "size": "2.1 M"
    },
    "12版：长三角·人物志·连载·广告.pdf": {
        "id": "i0rYy1wfs4yf",
        "size": "3.4 M"
    }
}