{
    "01版：封面.pdf": {
        "id": "inbI91woc1gh",
        "size": "2.8 M"
    },
    "02版：快评.pdf": {
        "id": "i0bGh1woc20h",
        "size": "623.4 K"
    },
    "03版：工会.pdf": {
        "id": "iruNI1woc1kb",
        "size": "920.1 K"
    },
    "04版：本市.pdf": {
        "id": "iDpZf1woc13e",
        "size": "560.3 K"
    },
    "05版：特写.pdf": {
        "id": "ihSSw1woc1of",
        "size": "525.1 K"
    },
    "06版_07版：顺义.pdf": {
        "id": "iRLkP1woc2cj",
        "size": "7.6 M"
    },
    "08版：文体.pdf": {
        "id": "iEtjU1woc1qh",
        "size": "609.9 K"
    },
    "09版：维权.pdf": {
        "id": "ijwBQ1woc22j",
        "size": "449.5 K"
    },
    "10版：综合.pdf": {
        "id": "in2DQ1woc1md",
        "size": "1.1 M"
    },
    "11版：生活.pdf": {
        "id": "iciEQ1woc24b",
        "size": "800.9 K"
    },
    "12版：视窗.pdf": {
        "id": "iKZJB1woc1xe",
        "size": "4.8 M"
    }
}