{
    "01版：封面.pdf": {
        "id": "iDwd61wnqd3e",
        "size": "2.2 M"
    },
    "02版：快评.pdf": {
        "id": "idsuN1wnqcte",
        "size": "599.5 K"
    },
    "03版：本市.pdf": {
        "id": "ifSBo1wnqcwh",
        "size": "669.0 K"
    },
    "04版：工会.pdf": {
        "id": "ilk1y1wnqd4f",
        "size": "726.7 K"
    },
    "05版：特写.pdf": {
        "id": "ii9Ll1wnqcsd",
        "size": "724.2 K"
    },
    "06版：大兴.pdf": {
        "id": "iIZra1wnqd6h",
        "size": "2.3 M"
    },
    "07版：西城.pdf": {
        "id": "i8AwJ1wnqcrc",
        "size": "1.1 M"
    },
    "08版：国内.pdf": {
        "id": "i6hoB1wnqcqb",
        "size": "563.5 K"
    },
    "09版：国际.pdf": {
        "id": "iFjvH1wnqcvg",
        "size": "523.5 K"
    },
    "10版：关注.pdf": {
        "id": "ijBKI1wnqd1c",
        "size": "438.6 K"
    },
    "11版：维权.pdf": {
        "id": "iEH0b1wnqcxi",
        "size": "368.5 K"
    },
    "12版：情怀.pdf": {
        "id": "i7O7W1wnqcza",
        "size": "1.6 M"
    }
}