{
    "A01版.pdf": {
        "id": "ihuw220trdda",
        "size": "5.2 M"
    },
    "A02版.pdf": {
        "id": "ilpV820trdpc",
        "size": "865.1 K"
    },
    "A03版.pdf": {
        "id": "iBxUy20tre0d",
        "size": "837.0 K"
    },
    "A04版.pdf": {
        "id": "i3lM420tregj",
        "size": "969.3 K"
    },
    "A05版.pdf": {
        "id": "iHhAP20trera",
        "size": "1,023.1 K"
    },
    "A06版.pdf": {
        "id": "ibQqg20trf3c",
        "size": "899.2 K"
    },
    "A07版.pdf": {
        "id": "i6YCK20trfih",
        "size": "881.6 K"
    },
    "A08版.pdf": {
        "id": "i3UaN20trfqf",
        "size": "1.1 M"
    },
    "A09版.pdf": {
        "id": "iR0h320trg4j",
        "size": "900.7 K"
    },
    "A10版.pdf": {
        "id": "iwkCp20trglg",
        "size": "1.1 M"
    },
    "A11版.pdf": {
        "id": "ihsBM20trgwh",
        "size": "5.3 M"
    },
    "A12版.pdf": {
        "id": "iLtHa20trhcd",
        "size": "6.5 M"
    },
    "A13版.pdf": {
        "id": "i7LZp20trhof",
        "size": "917.4 K"
    },
    "A14版.pdf": {
        "id": "ioRn720trhyf",
        "size": "776.8 K"
    },
    "A15版.pdf": {
        "id": "iSMWm20triah",
        "size": "3.7 M"
    },
    "A16版.pdf": {
        "id": "iOT7D20trina",
        "size": "2.3 M"
    },
    "A17版.pdf": {
        "id": "i265u20trj3g",
        "size": "5.4 M"
    },
    "A18版.pdf": {
        "id": "i7hF620trjha",
        "size": "4.1 M"
    },
    "A19版.pdf": {
        "id": "iWPK920trjtc",
        "size": "900.9 K"
    },
    "A20版.pdf": {
        "id": "iDdkL20trkdc",
        "size": "6.2 M"
    },
    "A21版.pdf": {
        "id": "iRCum20trkrg",
        "size": "817.3 K"
    },
    "A22版.pdf": {
        "id": "iQok420trl8d",
        "size": "953.4 K"
    },
    "A23版.pdf": {
        "id": "ii3QH20trlje",
        "size": "1.4 M"
    },
    "A24版.pdf": {
        "id": "ikRLi20trlsd",
        "size": "843.2 K"
    },
    "A25版.pdf": {
        "id": "io8fP20trm8j",
        "size": "1.1 M"
    },
    "A26版.pdf": {
        "id": "i5lNM20trmkb",
        "size": "1.1 M"
    },
    "A27版.pdf": {
        "id": "iuctP20trmvc",
        "size": "1.0 M"
    },
    "A28版.pdf": {
        "id": "i8lEk20trnfc",
        "size": "1,007.6 K"
    },
    "A29版.pdf": {
        "id": "idWAV20trnuh",
        "size": "901.2 K"
    },
    "A30版.pdf": {
        "id": "i2yze20trocf",
        "size": "1,011.5 K"
    },
    "B01版.pdf": {
        "id": "i2KS020troxg",
        "size": "5.6 M"
    },
    "B02版.pdf": {
        "id": "iclbF20trpba",
        "size": "877.1 K"
    },
    "B03版.pdf": {
        "id": "iIafL20trpod",
        "size": "706.8 K"
    },
    "B04版.pdf": {
        "id": "iQJGJ20trpze",
        "size": "922.2 K"
    },
    "B05版.pdf": {
        "id": "i1jmk20trqid",
        "size": "5.0 M"
    },
    "B06版.pdf": {
        "id": "iwZxF20trqsd",
        "size": "887.2 K"
    },
    "B07版.pdf": {
        "id": "iVJQe20trqza",
        "size": "1.2 M"
    },
    "B08版.pdf": {
        "id": "iuFNh20trrgh",
        "size": "3.2 M"
    }
}