{
    "01版：要闻.pdf": {
        "id": "iUio61wxldof",
        "size": "941.3 K"
    },
    "02版：要闻.pdf": {
        "id": "ivdrY1wxldqh",
        "size": "875.0 K"
    },
    "03版：要闻.pdf": {
        "id": "iyoSa1wxldpg",
        "size": "610.5 K"
    },
    "04版：神州速览.pdf": {
        "id": "iaCUN1wxldri",
        "size": "817.4 K"
    },
    "05版：中国故事.pdf": {
        "id": "iUIz31wxldsj",
        "size": "983.3 K"
    },
    "06版：国际观察.pdf": {
        "id": "iKeC51wxldta",
        "size": "1.1 M"
    },
    "07版：文学观察.pdf": {
        "id": "iaFOH1wxldja",
        "size": "883.0 K"
    },
    "08版：海外学子.pdf": {
        "id": "iC5YC1wxldne",
        "size": "1.4 M"
    },
    "09版：科教观潮.pdf": {
        "id": "i3Aug1wxldgh",
        "size": "954.3 K"
    },
    "10版：追梦青岛.pdf": {
        "id": "i0uUL1wxldlc",
        "size": "1.1 M"
    },
    "11版：旅游天地.pdf": {
        "id": "ityWV1wxldij",
        "size": "1.4 M"
    },
    "12版：百姓话题.pdf": {
        "id": "izkks1wxldmd",
        "size": "691.9 K"
    }
}