{
    "01版：要闻.pdf": {
        "id": "idAlL1wfvg7i",
        "size": "1.3 M"
    },
    "02版：要闻.pdf": {
        "id": "iTLPD1wfvgab",
        "size": "2.3 M"
    },
    "03版：国内.pdf": {
        "id": "i14Sw1wfvfvg",
        "size": "1.4 M"
    },
    "04版：专题.pdf": {
        "id": "iVgtr1wfvghi",
        "size": "3.2 M"
    },
    "05版：焦点.pdf": {
        "id": "ih2rc1wfvfxi",
        "size": "2.8 M"
    },
    "06版：上海.pdf": {
        "id": "iNTgc1wfvgef",
        "size": "2.6 M"
    },
    "07版：上海·广告.pdf": {
        "id": "izyFN1wfvg5g",
        "size": "2.2 M"
    },
    "08版：国际.pdf": {
        "id": "inT5U1wfvg3e",
        "size": "1.8 M"
    },
    "09版：朝花周刊·评论.pdf": {
        "id": "iHSbj1wfvg9a",
        "size": "1.3 M"
    },
    "10版：朝花周刊·夕拾·连载·广告.pdf": {
        "id": "ijO7x1wfvfza",
        "size": "1.4 M"
    },
    "11版：朝花周刊·综合·广告.pdf": {
        "id": "iHwfn1wfvfuf",
        "size": "2.0 M"
    },
    "12版：专题.pdf": {
        "id": "iLfqH1wfvg1c",
        "size": "2.5 M"
    }
}