{
    "01版：头版.pdf": {
        "id": "i7DKL29y1yof",
        "size": "1.2 M"
    },
    "02版：要闻.pdf": {
        "id": "iK35929y1yzg",
        "size": "589.1 K"
    },
    "03版：时事.pdf": {
        "id": "irX9329y1zbi",
        "size": "2.4 M"
    },
    "04版：地方新闻.pdf": {
        "id": "i5LTa29y1zli",
        "size": "3.5 M"
    },
    "05版：社会民生.pdf": {
        "id": "iHj9X29y1zwj",
        "size": "5.0 M"
    },
    "06版：专刊.pdf": {
        "id": "is8ts29y201e",
        "size": "1.5 M"
    },
    "07版：副刊·文苑.pdf": {
        "id": "i7Fa329y208b",
        "size": "1.3 M"
    },
    "08版：文体新闻·广告.pdf": {
        "id": "iIfKO29y20fi",
        "size": "2.5 M"
    }
}