{
    "01版：要闻.pdf": {
        "id": "i22zJ1wx8a5a",
        "size": "817.2 K"
    },
    "02版：要闻.pdf": {
        "id": "iet1y1wx8a7c",
        "size": "1.4 M"
    },
    "03版：要闻·财经.pdf": {
        "id": "iyj9m1wx89xc",
        "size": "930.2 K"
    },
    "04版：要闻·台港澳.pdf": {
        "id": "iVs8H1wx89ze",
        "size": "1,015.0 K"
    },
    "05版：焦点关注.pdf": {
        "id": "iwtch1wx8a1g",
        "size": "2.3 M"
    },
    "06版：华侨华人.pdf": {
        "id": "iSVka1wx89ti",
        "size": "948.4 K"
    },
    "07版：文学观察.pdf": {
        "id": "iTUXI1wx8a3i",
        "size": "767.3 K"
    },
    "08版：网络世界.pdf": {
        "id": "ibUJx1wx8a6b",
        "size": "846.1 K"
    },
    "09版：体坛风云.pdf": {
        "id": "i7PrI1wx8a8d",
        "size": "920.5 K"
    },
    "10版：科教观潮.pdf": {
        "id": "irhhn1wx89wb",
        "size": "1,015.4 K"
    },
    "11版：神州速览.pdf": {
        "id": "iezWV1wx8a2h",
        "size": "1.1 M"
    },
    "12版：旅游天地.pdf": {
        "id": "i686Y1wx89va",
        "size": "1.1 M"
    }
}