{
    "A01版：要聞.pdf": {
        "id": "iwQyx1vw97ja",
        "size": "622.9 K"
    },
    "A02版：要聞.pdf": {
        "id": "imSsH1vw97kb",
        "size": "608.6 K"
    },
    "A03版：要聞.pdf": {
        "id": "inSK71vw97lc",
        "size": "598.6 K"
    },
    "A04版：要聞.pdf": {
        "id": "iOAPP1vw97md",
        "size": "679.8 K"
    },
    "A05版：要聞.pdf": {
        "id": "iXql61vw97ne",
        "size": "667.1 K"
    },
    "A06版：要聞.pdf": {
        "id": "ijzVn1vw97pg",
        "size": "684.4 K"
    },
    "A07版：國際.pdf": {
        "id": "iZEki1vw97qh",
        "size": "624.8 K"
    },
    "A08版：經濟.pdf": {
        "id": "iOagn1vw97sj",
        "size": "654.7 K"
    },
    "A09版：廣告.pdf": {
        "id": "im0hV1vw97ub",
        "size": "286.4 K"
    },
    "A10版：中國.pdf": {
        "id": "iXmLu1vw97vc",
        "size": "735.2 K"
    },
    "A11版：雨岸.pdf": {
        "id": "iNxu61vw97wd",
        "size": "666.6 K"
    },
    "A12版：專題.pdf": {
        "id": "iWnlp1vw97yf",
        "size": "627.0 K"
    },
    "A13版：中國·新園地.pdf": {
        "id": "iUAh91vw981i",
        "size": "790.2 K"
    },
    "A14版：大公園.pdf": {
        "id": "isIaI1vw982j",
        "size": "624.6 K"
    },
    "A15版：副刊.pdf": {
        "id": "iy91O1vw983a",
        "size": "721.0 K"
    },
    "A16版：副刊.pdf": {
        "id": "ipGyf1vw986d",
        "size": "857.7 K"
    },
    "A17版：體育.pdf": {
        "id": "iiVZb1vw987e",
        "size": "915.4 K"
    },
    "A18版：體育.pdf": {
        "id": "ixEjr1vw989g",
        "size": "772.4 K"
    },
    "A19版：體育.pdf": {
        "id": "iMom21vw98ah",
        "size": "614.2 K"
    },
    "A20版：國際.pdf": {
        "id": "iGUI71vw98bi",
        "size": "650.7 K"
    }
}