{
    "01版：要闻.pdf": {
        "id": "itbSo1weou7e",
        "size": "691.8 K"
    },
    "02版：要闻.pdf": {
        "id": "iwKwY1weou9g",
        "size": "963.3 K"
    },
    "03版：要闻.pdf": {
        "id": "iUz4e1weou0h",
        "size": "723.8 K"
    },
    "04版：要闻.pdf": {
        "id": "iVv7t1weou6d",
        "size": "932.8 K"
    },
    "05版：军人家庭.pdf": {
        "id": "imaaW1weou2j",
        "size": "1.3 M"
    },
    "06版：文化生活.pdf": {
        "id": "izXLB1weou8f",
        "size": "896.2 K"
    },
    "07版：军人健康.pdf": {
        "id": "iRWlP1weouah",
        "size": "805.8 K"
    },
    "08版：长征副刊.pdf": {
        "id": "igg8d1weou5c",
        "size": "926.3 K"
    }
}