{
    "A01版：头条要闻.pdf": {
        "id": "iWGqL1wrz34d",
        "size": "2.2 M"
    },
    "A02版：本市新闻.pdf": {
        "id": "ipngg1wrz2zi",
        "size": "1.4 M"
    },
    "A03版：本市新闻.pdf": {
        "id": "iiyYI1wrz36f",
        "size": "2.1 M"
    },
    "A04版：国内新闻.pdf": {
        "id": "iIhVA1wrz37g",
        "size": "956.3 K"
    },
    "A05版：国际新闻.pdf": {
        "id": "iF7ge1wrz30j",
        "size": "1.1 M"
    },
    "A06版：今日关注.pdf": {
        "id": "iiqsC1wrz35e",
        "size": "1.2 M"
    },
    "A07版：体育新闻.pdf": {
        "id": "ikb8k1wrz33c",
        "size": "1.2 M"
    },
    "A08版：文娱新闻.pdf": {
        "id": "i05Ka1wrz32b",
        "size": "6.0 M"
    }
}