{
    "A01版.pdf": {
        "id": "iVxng20kieej",
        "size": "823.0 K"
    },
    "A02版.pdf": {
        "id": "icQaZ20kif7i",
        "size": "901.0 K"
    },
    "A03版.pdf": {
        "id": "inPsl20kifzg",
        "size": "804.9 K"
    },
    "A04版.pdf": {
        "id": "irdHW20kigob",
        "size": "789.5 K"
    },
    "A05版.pdf": {
        "id": "iGaOB20kihdg",
        "size": "1.0 M"
    },
    "A06版.pdf": {
        "id": "ijP6v20kii4d",
        "size": "816.3 K"
    },
    "A07版.pdf": {
        "id": "i6Ay920kiixc",
        "size": "907.7 K"
    },
    "A08版.pdf": {
        "id": "iqTPK20kijyj",
        "size": "1.1 M"
    },
    "A09版.pdf": {
        "id": "inprb20kil2j",
        "size": "995.7 K"
    },
    "A10版.pdf": {
        "id": "i10cr20kilzc",
        "size": "864.5 K"
    },
    "A11版.pdf": {
        "id": "iR6ma20kimkd",
        "size": "954.0 K"
    },
    "A12版.pdf": {
        "id": "i3BrZ20kin4d",
        "size": "1.1 M"
    },
    "B01版.pdf": {
        "id": "iwbvB20kio8d",
        "size": "991.7 K"
    },
    "B02版.pdf": {
        "id": "iOiqJ20kip8j",
        "size": "842.9 K"
    },
    "B03版.pdf": {
        "id": "ipmnK20kiq3a",
        "size": "945.9 K"
    },
    "B04版.pdf": {
        "id": "i8KNG20kirbe",
        "size": "1.2 M"
    },
    "B05版.pdf": {
        "id": "iJndZ20kisaj",
        "size": "1.0 M"
    },
    "B06版.pdf": {
        "id": "id4Bw20kit6b",
        "size": "1.7 M"
    },
    "B07版.pdf": {
        "id": "imtDj20kitxi",
        "size": "904.9 K"
    },
    "B08版.pdf": {
        "id": "iZ0f020kiuvc",
        "size": "2.7 M"
    },
    "C01版.pdf": {
        "id": "i4QZc20kivjg",
        "size": "1.4 M"
    },
    "C02版.pdf": {
        "id": "igFlS20kiwad",
        "size": "1.1 M"
    },
    "C03版.pdf": {
        "id": "imEQC20kix4d",
        "size": "1.2 M"
    },
    "C04版.pdf": {
        "id": "irm6K20kiy0f",
        "size": "1.1 M"
    }
}