{
    "01版：头版.pdf": {
        "id": "ihc5E2a1bu5a",
        "size": "3.6 M"
    },
    "02版：要闻.pdf": {
        "id": "iN3hz2a1buej",
        "size": "560.1 K"
    },
    "03版：长春新闻.pdf": {
        "id": "iqTy22a1bumh",
        "size": "1.1 M"
    },
    "04版：时事.pdf": {
        "id": "iRSMG2a1buwh",
        "size": "2.2 M"
    },
    "05版：全面小康 魅力之都.pdf": {
        "id": "iNUVd2a1bvab",
        "size": "4.2 M"
    },
    "06版：文体新闻.pdf": {
        "id": "iPbkH2a1bvne",
        "size": "2.4 M"
    },
    "07版：副刊·文苑.pdf": {
        "id": "i0FSY2a1bvvc",
        "size": "1.7 M"
    },
    "08版：广告.pdf": {
        "id": "iXfb82a1bw9g",
        "size": "3.9 M"
    }
}