{
    "01版：头版.pdf": {
        "id": "ipwQ02a1b2he",
        "size": "5.3 M"
    },
    "02版：长春新闻.pdf": {
        "id": "iPx002a1b2ob",
        "size": "6.6 M"
    },
    "03版：长春新闻.pdf": {
        "id": "i7pax2a1b2xa",
        "size": "5.4 M"
    },
    "04版：长春新闻.pdf": {
        "id": "icv5N2a1b34h",
        "size": "5.6 M"
    },
    "05版：时事.pdf": {
        "id": "iAD2z2a1b3be",
        "size": "3.6 M"
    },
    "06版：全面小康 魅力之都.pdf": {
        "id": "iIxJ62a1b3ha",
        "size": "7.1 M"
    },
    "07版：文体新闻.pdf": {
        "id": "iSTIg2a1b3ng",
        "size": "1.8 M"
    },
    "08版：文旅视界.pdf": {
        "id": "i2TXE2a1b3qj",
        "size": "2.7 M"
    }
}