{
    "01版：一版要闻.pdf": {
        "id": "iv6Df1vfifof",
        "size": "2.7 M"
    },
    "02版：综合新闻.pdf": {
        "id": "iYc1t1vfifzg",
        "size": "791.9 K"
    },
    "03版：企业新闻.pdf": {
        "id": "ivyJK1vfig8f",
        "size": "953.0 K"
    },
    "04版：审查周刊.pdf": {
        "id": "inxhj1vfigif",
        "size": "634.1 K"
    },
    "05版：商标周刊.pdf": {
        "id": "iFz1i1vfigpc",
        "size": "815.1 K"
    },
    "06版：商标天下.pdf": {
        "id": "ilSvM1vfih6j",
        "size": "999.4 K"
    },
    "07版：商标风尚.pdf": {
        "id": "iqFkL1vfihgj",
        "size": "753.3 K"
    },
    "08版：理论视点.pdf": {
        "id": "iI6gi1vfihwf",
        "size": "772.6 K"
    },
    "09版：版权周刊.pdf": {
        "id": "iNcoB1vfii4d",
        "size": "781.8 K"
    },
    "10版：版权综合.pdf": {
        "id": "iGwp71vfiife",
        "size": "801.4 K"
    },
    "11版：版权专题.pdf": {
        "id": "iJpkw1vfiipe",
        "size": "1.3 M"
    },
    "12版：广告.pdf": {
        "id": "iinjX1vfijaf",
        "size": "4.7 M"
    },
    "13版：专版.pdf": {
        "id": "iLAqV1vfijhc",
        "size": "279.3 K"
    },
    "14版：专版.pdf": {
        "id": "ithwL1vfijpa",
        "size": "327.3 K"
    },
    "15版：专版.pdf": {
        "id": "i698B1vfijza",
        "size": "307.8 K"
    },
    "16版：专版.pdf": {
        "id": "ikxZV1vfik9a",
        "size": "293.4 K"
    }
}